napalm_eltex/__init__.py
napalm_eltex/eltex.py
napalm_eltex/usage.py
napalm_eltex-0.1.3.dist-info/AUTHORS
napalm_eltex-0.1.3.dist-info/LICENSE
napalm_eltex-0.1.3.dist-info/METADATA
napalm_eltex-0.1.3.dist-info/WHEEL
napalm_eltex-0.1.3.dist-info/top_level.txt
napalm_eltex-0.1.3.dist-info/RECORD
